spyker/__init__.py
spyker/module.py
spyker/private.py
spyker/sparse.py
spyker/spyker_plugin.cpython-313-x86_64-linux-gnu.so
spyker/utils.py
spyker.libs/libiomp5-31023e22.so
spyker.libs/libomp-4cd597c7.so
spyker-0.1.0.dist-info/METADATA
spyker-0.1.0.dist-info/WHEEL
spyker-0.1.0.dist-info/top_level.txt
spyker-0.1.0.dist-info/RECORD
spyker-0.1.0.dist-info/licenses/LICENSE
