Metadata-Version: 2.4
Name: spyker
Version: 0.1.0
Summary: Spiking Deep Neural Networks Library
Author-email: Shahriar Rezghi <shahriar.rezghi.sh@gmail.com>
License: BSD 3-Clause License
Project-URL: Homepage, https://github.com/ShahriarRezghi/Spyker
Keywords: cxx,high-performance,cuda,neuroscience,computational-neuroscience,cudnn,snn,stdp,onednn,r-stdp
Classifier: Environment :: GPU
Classifier: Environment :: GPU :: NVIDIA CUDA
Classifier: Programming Language :: C++
Classifier: Programming Language :: Python :: 3
Classifier: Programming Language :: Python :: 3.9
Classifier: Programming Language :: Python :: 3.10
Classifier: Programming Language :: Python :: 3.11
Classifier: Programming Language :: Python :: 3.12
Classifier: Programming Language :: Python :: 3.13
Classifier: Programming Language :: Python :: 3.14
Requires-Python: >=3.9
License-File: LICENSE
Provides-Extra: numpy
Requires-Dist: numpy>=1.20; extra == "numpy"
Provides-Extra: torch
Requires-Dist: torch>=1.12; extra == "torch"
Dynamic: license-file
